ament_cmake/_dummy.cpython-310-x86_64-linux-gnu.so
ros_ament_cmake-2.7.3.data/data/share/ament_cmake/local_setup.bash
ros_ament_cmake-2.7.3.data/data/share/ament_cmake/local_setup.dsv
ros_ament_cmake-2.7.3.data/data/share/ament_cmake/local_setup.sh
ros_ament_cmake-2.7.3.data/data/share/ament_cmake/local_setup.zsh
ros_ament_cmake-2.7.3.data/data/share/ament_cmake/package.dsv
ros_ament_cmake-2.7.3.data/data/share/ament_cmake/package.xml
ros_ament_cmake-2.7.3.data/data/share/ament_cmake/cmake/ament_cmakeConfig-version.cmake
ros_ament_cmake-2.7.3.data/data/share/ament_cmake/cmake/ament_cmakeConfig.cmake
ros_ament_cmake-2.7.3.data/data/share/ament_cmake/cmake/ament_cmake_export_dependencies-extras.cmake
ros_ament_cmake-2.7.3.data/data/share/ament_cmake/environment/ament_prefix_path.dsv
ros_ament_cmake-2.7.3.data/data/share/ament_cmake/environment/ament_prefix_path.sh
ros_ament_cmake-2.7.3.data/data/share/ament_cmake/environment/path.dsv
ros_ament_cmake-2.7.3.data/data/share/ament_cmake/environment/path.sh
ros_ament_cmake-2.7.3.data/data/share/ament_index/resource_index/package_run_dependencies/ament_cmake
ros_ament_cmake-2.7.3.data/data/share/ament_index/resource_index/packages/ament_cmake
ros_ament_cmake-2.7.3.data/data/share/ament_index/resource_index/parent_prefix_path/ament_cmake
ros_ament_cmake-2.7.3.dist-info/METADATA
ros_ament_cmake-2.7.3.dist-info/WHEEL
ros_ament_cmake-2.7.3.dist-info/top_level.txt
ros_ament_cmake-2.7.3.dist-info/RECORD
