Metadata-Version: 2.4
Name: ros-ament-cmake
Version: 2.7.3
Summary: Wheel for the ament_cmake (ros-ament-cmake) ROS 2 package.
Requires-Dist: ros-ament-cmake-test~=2.7.3
Requires-Dist: ros-ament-cmake-export-definitions~=2.7.3
Requires-Dist: ros-ament-cmake-version~=2.7.3
Requires-Dist: ros-ament-cmake-export-include-directories~=2.7.3
Requires-Dist: ros-ament-cmake-export-libraries~=2.7.3
Requires-Dist: ros-ament-cmake-export-interfaces~=2.7.3
Requires-Dist: ros-ament-cmake-export-targets~=2.7.3
Requires-Dist: ros-ament-cmake-target-dependencies~=2.7.3
Requires-Dist: ros-ament-cmake-libraries~=2.7.3
Requires-Dist: ros-ament-cmake-export-dependencies~=2.7.3
Requires-Dist: ros-ament-cmake-export-link-flags~=2.7.3
Requires-Dist: ros-ament-cmake-gen-version-h~=2.7.3
Requires-Dist: ros-ament-cmake-python~=2.7.3
Requires-Dist: ros-ament-cmake-core~=2.7.3
Dynamic: description
Dynamic: description-content-type
Dynamic: requires-dist
Dynamic: summary
